[
  {
    "question": "What is the definition of learning?",
    "options": {
      "A": "A temporary change in behavior due to external stimuli.",
      "B": "A relatively lasting change in behavior or knowledge resulting from experience.",
      "C": "An innate ability to perform complex tasks.",
      "D": "The process of acquiring information through reading and memorization."
    },
    "answer": "B",
    "explanation": "Learning involves a durable change in behavior or knowledge that arises from experience."
  },
  {
    "question": "Which of the following is NOT a type of learning?",
    "options": {
      "A": "Associative learning",
      "B": "Non-associative learning",
      "C": "Instinctive behavior",
      "D": "Observational learning"
    },
    "answer": "C",
    "explanation": "Instinctive behaviors are innate and not learned."
  },
  {
    "question": "What is habituation?",
    "options": {
      "A": "An increase in behavioral response to a repeated stimulus.",
      "B": "A decrease in behavioral response to a repeated stimulus.",
      "C": "The formation of an association between two stimuli.",
      "D": "Learning through observing others."
    },
    "answer": "B",
    "explanation": "Habituation is the reduction of a behavioral response after prolonged or repeated exposure to a stimulus."
  },
  {
    "question": "What is sensitization?",
    "options": {
      "A": "A decrease in behavioral response to a repeated stimulus.",
      "B": "An increase in behavioral response to a repeated stimulus.",
      "C": "The weakening of a conditioned response.",
      "D": "The return of a conditioned response after extinction."
    },
    "answer": "B",
    "explanation": "Sensitization refers to the intensification of a behavioral response after prolonged or repeated exposure to a stimulus."
  },
  {
    "question": "Which of the following is an example of non-associative learning?",
    "options": {
      "A": "A dog learning to sit for a treat.",
      "B": "A child developing a fear of dogs after being bitten.",
      "C": "A person becoming accustomed to the sound of traffic outside their window.",
      "D": "A student memorizing multiplication tables."
    },
    "answer": "C",
    "explanation": "Getting used to the sound of traffic involves learning about a single stimulus without associating it with anything else."
  },
  {
    "question": "What is associative learning?",
    "options": {
      "A": "Learning about a single stimulus.",
      "B": "Learning the relationship between two pieces of information.",
      "C": "Learning through trial and error.",
      "D": "Learning by observing others."
    },
    "answer": "B",
    "explanation": "Associative learning focuses on understanding the connections between two pieces of information."
  },
  {
    "question": "What are the two main types of associative learning?",
    "options": {
      "A": "Classical conditioning and habituation.",
      "B": "Operant conditioning and sensitization.",
      "C": "Classical conditioning and operant conditioning.",
      "D": "Observational learning and habituation."
    },
    "answer": "C",
    "explanation": "Associative learning encompasses classical and operant conditioning."
  },
  {
    "question": "What is classical conditioning?",
    "options": {
      "A": "Learning that a behavior leads to a specific outcome.",
      "B": "Learning that a stimulus predicts another stimulus.",
      "C": "Learning through trial and error.",
      "D": "Learning by observing others."
    },
    "answer": "B",
    "explanation": "Classical conditioning involves learning that one stimulus signals the arrival of another stimulus."
  },
  {
    "question": "In Pavlov's experiment, what was the unconditioned stimulus?",
    "options": {
      "A": "The bell",
      "B": "The food",
      "C": "Salivation in response to the bell",
      "D": "Salivation in response to the food"
    },
    "answer": "B",
    "explanation": "The food naturally elicited salivation without prior learning, making it the unconditioned stimulus."
  },
  {
    "question": "In Pavlov's experiment, what was the conditioned stimulus?",
    "options": {
      "A": "The bell",
      "B": "The food",
      "C": "Salivation in response to the bell",
      "D": "Salivation in response to the food"
    },
    "answer": "A",
    "explanation": "The bell initially elicited no response but came to trigger salivation after being paired with the food."
  },
  {
    "question": "What is the conditioned response?",
    "options": {
      "A": "An instinctive reaction to a stimulus.",
      "B": "A learned reaction to a previously neutral stimulus.",
      "C": "The weakening of a learned response.",
      "D": "The strengthening of an instinctive response."
    },
    "answer": "B",
    "explanation": "The conditioned response is a learned reaction triggered by a stimulus that was previously neutral."
  },
  {
    "question": "What is acquisition in classical conditioning?",
    "options": {
      "A": "The weakening of a conditioned response.",
      "B": "The return of a conditioned response after extinction.",
      "C": "The gradual formation of an association between the unconditioned stimulus and the conditioned stimulus.",
      "D": "The use of classical conditioning to treat phobias."
    },
    "answer": "C",
    "explanation": "Acquisition is the process of learning the association between the unconditioned stimulus and the conditioned stimulus."
  },
  {
    "question": "What is extinction in classical conditioning?",
    "options": {
      "A": "The strengthening of a conditioned response.",
      "B": "The weakening or elimination of a conditioned response.",
      "C": "The formation of a new conditioned response.",
      "D": "The generalization of a conditioned response to similar stimuli."
    },
    "answer": "B",
    "explanation": "Extinction occurs when the conditioned response diminishes or disappears because the conditioned stimulus is repeatedly presented without the unconditioned stimulus."
  },
  {
    "question": "What is spontaneous recovery in classical conditioning?",
    "options": {
      "A": "The formation of a new conditioned response.",
      "B": "The generalization of a conditioned response to similar stimuli.",
      "C": "The re-emergence of a conditioned response following a period without exposure to the conditioned stimulus after extinction.",
      "D": "The weakening of a conditioned response due to repeated exposure to the conditioned stimulus without the unconditioned stimulus."
    },
    "answer": "C",
    "explanation": "Spontaneous recovery refers to the reappearance of a conditioned response after a pause in exposure to the conditioned stimulus following extinction."
  },
  {
    "question": "What is second-order conditioning?",
    "options": {
      "A": "The weakening of a conditioned response.",
      "B": "A conditioned stimulus functioning as if it were an unconditioned stimulus.",
      "C": "The generalization of a conditioned response to similar stimuli.",
      "D": "The prevention of conditioning to a new stimulus when combined with a previous conditioned stimulus."
    },
    "answer": "B",
    "explanation": "In second-order conditioning, a conditioned stimulus takes on the role of an unconditioned stimulus, eliciting the conditioned response without the original unconditioned stimulus."
  },
  {
    "question": "What is blocking in classical conditioning?",
    "options": {
      "A": "The strengthening of a conditioned response.",
      "B": "The weakening of a conditioned response.",
      "C": "The prevention of conditioning to a new stimulus when it is presented along with a previously conditioned stimulus.",
      "D": "The generalization of a conditioned response to similar stimuli."
    },
    "answer": "C",
    "explanation": "Blocking occurs when an existing conditioned stimulus prevents a new stimulus from becoming conditioned when they are presented together."
  },
  {
    "question": "Which of the following is an example of classical conditioning in humans?",
    "options": {
      "A": "A child learning to ride a bike.",
      "B": "A student studying for an exam.",
      "C": "A person developing a fear of spiders after being bitten.",
      "D": "A dog learning to fetch a ball."
    },
    "answer": "C",
    "explanation": "Developing a fear of spiders after being bitten demonstrates an association between the spider (conditioned stimulus) and the pain of the bite (unconditioned stimulus), leading to fear (conditioned response)."
  },
  {
    "question": "What is taste aversion conditioning?",
    "options": {
      "A": "A preference for certain flavors based on cultural influences.",
      "B": "An association between flavors and the positive consequences of eating.",
      "C": "An association between flavors and the negative consequences of eating.",
      "D": "The ability to distinguish between different tastes."
    },
    "answer": "C",
    "explanation": "Taste aversion conditioning involves linking flavors with unpleasant experiences, such as feeling sick after consuming something."
  },
  {
    "question": "How does fear conditioning contribute to anxiety disorders?",
    "options": {
      "A": "It helps individuals cope with stressful situations.",
      "B": "It allows people to learn from their mistakes.",
      "C": "It leads to an excessive fear of harmless objects or situations.",
      "D": "It promotes relaxation and reduces anxiety."
    },
    "answer": "C",
    "explanation": "Fear conditioning can cause individuals to associate certain cues with panic or intense emotions, leading to phobias or panic disorders."
  },
  {
    "question": "What is systematic desensitization?",
    "options": {
      "A": "A technique for increasing anxiety in controlled settings.",
      "B": "A treatment for phobias that involves gradual exposure to the feared stimulus.",
      "C": "A method for suppressing unwanted thoughts and feelings.",
      "D": "A form of punishment used to reduce undesirable behaviors."
    },
    "answer": "B",
    "explanation": "Systematic desensitization aims to treat phobias by gradually exposing individuals to the feared object or situation while promoting relaxation."
  },
  {
    "question": "In the YouTube video about snake phobia therapy, how was Mariam's fear of snakes addressed?",
    "options": {
      "A": "Through medication and talk therapy.",
      "B": "Through hypnosis and dream analysis.",
      "C": "Through progressive exposure to a snake in a safe environment.",
      "D": "Through avoidance of any contact with snakes."
    },
    "answer": "C",
    "explanation": "Mariam participated in exposure therapy, which involved gradually interacting with a snake while challenging her fear-based beliefs."
  },
  {
    "question": "According to the YouTube video, what is the role of maintenance in treating phobias?",
    "options": {
      "A": "It prevents the phobia from returning.",
      "B": "It increases the intensity of the phobia.",
      "C": "It involves completely avoiding the feared stimulus.",
      "D": "It has no impact on the effectiveness of the therapy."
    },
    "answer": "A",
    "explanation": "Maintenance activities, such as watching nature documentaries or visiting zoos, can help reinforce the positive outcomes of exposure therapy."
  },
  {
    "question": "In the 'Learning Theories Example – 1,' what type of learning is exemplified by becoming increasingly annoyed by the speaker's repeated use of 'okay'?",
    "options": {
      "A": "Habituation",
      "B": "Sensitization",
      "C": "Classical conditioning",
      "D": "Operant conditioning"
    },
    "answer": "B",
    "explanation": "The repeated 'okay' leads to heightened annoyance, indicating an increase in behavioral response, which aligns with sensitization."
  },
  {
    "question": "In Chris's aversion to oysters, what is the conditioned stimulus?",
    "options": {
      "A": "Eating oysters at age 5",
      "B": "The stomach flu",
      "C": "The smell of oysters or thinking about eating them",
      "D": "Feeling nauseated and sick"
    },
    "answer": "C",
    "explanation": "The smell or thought of oysters now triggers nausea, making it the conditioned stimulus."
  },
  {
    "question": "In the example of feeling like it's lunchtime when a colleague announces it, what is the unconditioned stimulus?",
    "options": {
      "A": "The colleague's announcement",
      "B": "12 pm",
      "C": "Feeling like it's lunchtime",
      "D": "11 am"
    },
    "answer": "B",
    "explanation": "12 pm is the time that naturally elicits the feeling of lunchtime without any conditioning."
  },
  {
    "question": "What is operant conditioning?",
    "options": {
      "A": "Learning that a stimulus predicts another stimulus.",
      "B": "Learning through observation.",
      "C": "Learning by associating a behavior with its consequences.",
      "D": "Learning through trial and error."
    },
    "answer": "C",
    "explanation": "Operant conditioning focuses on understanding how the consequences of a behavior influence the likelihood of repeating that behavior."
  },
  {
    "question": "What is a reinforcer?",
    "options": {
      "A": "A stimulus that weakens a behavior.",
      "B": "A consequence of an action that affects the likelihood of the behavior being repeated.",
      "C": "A neutral stimulus that elicits no response.",
      "D": "An unlearned behavior."
    },
    "answer": "B",
    "explanation": "A reinforcer is anything that follows a behavior and influences its future occurrence."
  },
  {
    "question": "What is the Skinner box?",
    "options": {
      "A": "A type of maze used to study learning in rats.",
      "B": "A controlled environment used to study operant conditioning in animals.",
      "C": "A tool for measuring intelligence in humans.",
      "D": "A device for recording brain activity."
    },
    "answer": "B",
    "explanation": "The Skinner box provides a controlled setting for observing and manipulating animal behavior in operant conditioning experiments."
  },
  {
    "question": "What are the four types of reinforcement and punishment?",
    "options": {
      "A": "Positive, negative, neutral, and variable.",
      "B": "Fixed, variable, ratio, and interval.",
      "C": "Continuous, partial, intermittent, and random.",
      "D": "Positive reinforcement, positive punishment, negative reinforcement, and negative punishment."
    },
    "answer": "D",
    "explanation": "These four types categorize the ways in which consequences can be added or removed to increase or decrease behaviors."
  },
  {
    "question": "What is positive reinforcement?",
    "options": {
      "A": "Adding a stimulus to increase a behavior.",
      "B": "Removing a stimulus to increase a behavior.",
      "C": "Adding a stimulus to decrease a behavior.",
      "D": "Removing a stimulus to decrease a behavior."
    },
    "answer": "A",
    "explanation": "Positive reinforcement involves presenting a rewarding stimulus after a desired behavior to make it more likely to happen again."
  },
  {
    "question": "What is negative reinforcement?",
    "options": {
      "A": "Adding a stimulus to increase a behavior.",
      "B": "Removing a stimulus to increase a behavior.",
      "C": "Adding a stimulus to decrease a behavior.",
      "D": "Removing a stimulus to decrease a behavior."
    },
    "answer": "B",
    "explanation": "Negative reinforcement involves taking away an unpleasant stimulus after a desired behavior, making that behavior more likely to occur in the future."
  },
  {
    "question": "What is positive punishment?",
    "options": {
      "A": "Adding a stimulus to increase a behavior.",
      "B": "Removing a stimulus to increase a behavior.",
      "C": "Adding a stimulus to decrease a behavior.",
      "D": "Removing a stimulus to decrease a behavior."
    },
    "answer": "C",
    "explanation": "Positive punishment involves adding an aversive stimulus after an undesirable behavior to decrease the likelihood of that behavior happening again."
  },
  {
    "question": "What is negative punishment?",
    "options": {
      "A": "Adding a stimulus to increase a behavior.",
      "B": "Removing a stimulus to increase a behavior.",
      "C": "Adding a stimulus to decrease a behavior.",
      "D": "Removing a stimulus to decrease a behavior."
    },
    "answer": "D",
    "explanation": "Negative punishment involves taking away a desirable stimulus after an undesirable behavior to reduce the likelihood of that behavior occurring again."
  },
  {
    "question": "Which type of reinforcement leads to faster learning but is less common in real life?",
    "options": {
      "A": "Continuous reinforcement",
      "B": "Partial reinforcement",
      "C": "Positive reinforcement",
      "D": "Negative reinforcement"
    },
    "answer": "A",
    "explanation": "Continuous reinforcement results in rapid learning but is not very sustainable as the behavior extinguishes quickly when the reinforcement stops."
  },
  {
    "question": "What are the four schedules of reinforcement?",
    "options": {
      "A": "Fixed interval, variable interval, fixed ratio, and variable ratio.",
      "B": "Positive, negative, continuous, and partial.",
      "C": "Reward, punishment, acquisition, and extinction.",
      "D": "Classical, operant, observational, and non-associative."
    },
    "answer": "A",
    "explanation": "These schedules categorize reinforcement based on whether they relate to time (interval) or number of responses (ratio) and whether they are predictable (fixed) or unpredictable (variable)."
  },
  {
    "question": "Which schedule of reinforcement is illustrated by receiving a paycheck every two weeks?",
    "options": {
      "A": "Fixed interval",
      "B": "Variable interval",
      "C": "Fixed ratio",
      "D": "Variable ratio"
    },
    "answer": "A",
    "explanation": "The paycheck occurs at a predictable time interval (every two weeks)."
  },
  {
    "question": "Which schedule of reinforcement is exemplified by a slot machine paying out after an unpredictable number of plays?",
    "options": {
      "A": "Fixed interval",
      "B": "Variable interval",
      "C": "Fixed ratio",
      "D": "Variable ratio"
    },
    "answer": "D",
    "explanation": "The payout depends on the number of responses (plays) and is unpredictable (variable)."
  },
  {
    "question": "What is shaping in operant conditioning?",
    "options": {
      "A": "Punishing undesirable behaviors.",
      "B": "Ignoring unwanted behaviors.",
      "C": "Reinforcing behaviors that are increasingly similar to the desired behavior.",
      "D": "Teaching complex behaviors all at once."
    },
    "answer": "C",
    "explanation": "Shaping involves reinforcing successive approximations of a target behavior to gradually teach it."
  },
  {
    "question": "What is the quantitative law of effect?",
    "options": {
      "A": "The strength of a behavior is determined by its consequences.",
      "B": "Reinforcing one behavior affects the likelihood of other behaviors.",
      "C": "Behaviors with more favorable outcomes are more likely to be repeated.",
      "D": "Punishment is more effective than reinforcement."
    },
    "answer": "B",
    "explanation": "The quantitative law of effect highlights that the effectiveness of reinforcing one behavior depends on the reinforcement available for alternative behaviors."
  },
  {
    "question": "Why is positive punishment often ineffective?",
    "options": {
      "A": "It can lead to negative emotions and resentment.",
      "B": "It may inadvertently punish desirable behaviors.",
      "C": "It does not teach alternative behaviors.",
      "D": "All of the above"
    },
    "answer": "D",
    "explanation": "Positive punishment can have several drawbacks, including emotional consequences, misapplication, and a lack of guidance towards appropriate behaviors."
  },
  {
    "question": "What is behavioral modification?",
    "options": {
      "A": "The study of animal behavior in natural settings.",
      "B": "The use of operant conditioning techniques to change behavior.",
      "C": "A form of therapy that focuses on unconscious conflicts.",
      "D": "A method for measuring personality traits."
    },
    "answer": "B",
    "explanation": "Behavioral modification employs operant conditioning principles to eliminate undesirable behaviors and replace them with desirable ones."
  },
  {
    "question": "What is token economics?",
    "options": {
      "A": "A system of using rewards to motivate behavior.",
      "B": "A form of punishment used to deter undesirable behaviors.",
      "C": "A method for teaching language skills.",
      "D": "A technique for measuring intelligence."
    },
    "answer": "A",
    "explanation": "Token economics uses tokens or points as rewards for desired behaviors, which can be exchanged for privileges or desired items."
  },
  {
    "question": "What is observational learning?",
    "options": {
      "A": "Learning by associating a behavior with its consequences.",
      "B": "Learning by watching others.",
      "C": "Learning through trial and error.",
      "D": "Learning through classical conditioning."
    },
    "answer": "B",
    "explanation": "Observational learning involves acquiring or modifying behavior after witnessing others perform that behavior."
  },
  {
    "question": "Who are social models in observational learning?",
    "options": {
      "A": "Individuals who are being observed.",
      "B": "People who discourage learning.",
      "C": "Individuals of lower status than the learner.",
      "D": "Individuals of higher status or authority who serve as targets for observation and modeling."
    },
    "answer": "D",
    "explanation": "Social models are typically people in positions of influence or authority whom learners observe and imitate."
  },
  {
    "question": "What was the main hypothesis of Bandura's Bobo Doll studies?",
    "options": {
      "A": "Children are naturally aggressive.",
      "B": "Children can learn aggressive behaviors through observation.",
      "C": "Watching violence reduces aggression in children.",
      "D": "Punishment is the most effective way to reduce aggression."
    },
    "answer": "B",
    "explanation": "Bandura's studies aimed to investigate whether children would imitate aggressive behavior after observing an adult model."
  },
  {
    "question": "What did Bandura's Bobo Doll studies demonstrate?",
    "options": {
      "A": "Children exposed to aggressive models were less likely to be aggressive.",
      "B": "Children exposed to aggressive models showed more interest in aggressive behaviors.",
      "C": "Observation had no effect on children's behavior.",
      "D": "Rewarding aggressive behavior reduced its occurrence."
    },
    "answer": "B",
    "explanation": "The studies revealed that children who witnessed aggressive behavior were more likely to engage in similar aggressive actions themselves."
  },
  {
    "question": "What is a potential implication of Bandura's Bobo Doll studies?",
    "options": {
      "A": "Violence in media has no impact on children's behavior.",
      "B": "Exposure to violence can encourage aggressive behavior in children.",
      "C": "Aggression is solely determined by genetics.",
      "D": "Children are incapable of learning through observation."
    },
    "answer": "B",
    "explanation": "The findings suggest that witnessing violence can contribute to the learning and adoption of aggressive behaviors in children."
  },
  {
    "question": "In Sarah's case of being late and texting during meetings, what type of operant conditioning is her boss using?",
    "options": {
      "A": "Positive reinforcement",
      "B": "Negative reinforcement",
      "C": "Positive punishment",
      "D": "Negative punishment"
    },
    "answer": "D",
    "explanation": "Sarah's boss is removing privileges (a desirable stimulus) to decrease her undesirable behaviors."
  },
  {
    "question": "What type of operant conditioning is illustrated by video games rewarding players for completing tasks?",
    "options": {
      "A": "Positive reinforcement",
      "B": "Negative reinforcement",
      "C": "Positive punishment",
      "D": "Negative punishment"
    },
    "answer": "A",
    "explanation": "The game adds points or tokens (a desirable stimulus) to increase the likelihood of players continuing to play and complete tasks."
  },
  {
    "question": "In Eric's case of avoiding loud concerts, what type of operant conditioning is taking place?",
    "options": {
      "A": "Positive reinforcement",
      "B": "Negative reinforcement",
      "C": "Positive punishment",
      "D": "Negative punishment"
    },
    "answer": "B",
    "explanation": "Eric is removing himself from the unpleasant stimulus of loud music, increasing the likelihood of avoiding concerts in the future."
  },
  {
    "question": "What type of operant conditioning is demonstrated by a dog owner shouting at their dog for running away?",
    "options": {
      "A": "Positive reinforcement",
      "B": "Negative reinforcement",
      "C": "Positive punishment",
      "D": "Negative punishment"
    },
    "answer": "C",
    "explanation": "The owner is adding a shouting (an aversive stimulus) to decrease the dog's running away behavior."
  },
  {
    "question": "What type of learning explains Sam's ability to swing a baseball bat even though he has never done it before?",
    "options": {
      "A": "Classical conditioning",
      "B": "Operant conditioning",
      "C": "Observational learning",
      "D": "Non-associative learning"
    },
    "answer": "C",
    "explanation": "Sam has likely learned how to swing a bat by watching others do it, even without direct experience."
  }
]
